docker_pull_limit_exporter/__init__.py
docker_pull_limit_exporter-0.1.0.dev1.dist-info/LICENSE
docker_pull_limit_exporter-0.1.0.dev1.dist-info/METADATA
docker_pull_limit_exporter-0.1.0.dev1.dist-info/WHEEL
docker_pull_limit_exporter-0.1.0.dev1.dist-info/entry_points.txt
docker_pull_limit_exporter-0.1.0.dev1.dist-info/top_level.txt
docker_pull_limit_exporter-0.1.0.dev1.dist-info/RECORD
